{
  "formatVersion": 1,
  "database": {
    "version": 4,
    "identityHash": "e159e5c263765134655d74ff72689d00",
    "entities": [
      {
        "tableName": "table_issues",
        "createSql": "CREATE TABLE IF NOT EXISTS `${TABLE_NAME}` (`id` INTEGER PRIMARY KEY AUTOINCREMENT NOT NULL, `issue` INTEGER NOT NULL)",
        "fields": [
          {
            "fieldPath": "id",
            "columnName": "id",
            "affinity": "INTEGER",
            "notNull": true
          },
          {
            "fieldPath": "issue",
            "columnName": "issue",
            "affinity": "INTEGER",
            "notNull": true
          }
        ],
        "primaryKey": {
          "autoGenerate": true,
          "columnNames": [
            "id"
          ]
        },
        "indices": [],
        "foreignKeys": []
      },
      {
        "tableName": "table_tickets",
        "createSql": "CREATE TABLE IF NOT EXISTS `${TABLE_NAME}` (`id` INTEGER PRIMARY KEY AUTOINCREMENT NOT NULL, `ticket` TEXT NOT NULL, `issue_id` INTEGER NOT NULL, FOREIGN KEY(`issue_id`) REFERENCES `table_issues`(`id`) ON UPDATE NO ACTION ON DELETE CASCADE )",
        "fields": [
          {
            "fieldPath": "id",
            "columnName": "id",
            "affinity": "INTEGER",
            "notNull": true
          },
          {
            "fieldPath": "ticket",
            "columnName": "ticket",
            "affinity": "TEXT",
            "notNull": true
          },
          {
            "fieldPath": "issue_id",
            "columnName": "issue_id",
            "affinity": "INTEGER",
            "notNull": true
          }
        ],
        "primaryKey": {
          "autoGenerate": true,
          "columnNames": [
            "id"
          ]
        },
        "indices": [],
        "foreignKeys": [
          {
            "table": "table_issues",
            "onDelete": "CASCADE",
            "onUpdate": "NO ACTION",
            "columns": [
              "issue_id"
            ],
            "referencedColumns": [
              "id"
            ]
          }
        ]
      },
      {
        "tableName": "table_numbers",
        "createSql": "CREATE TABLE IF NOT EXISTS `${TABLE_NAME}` (`id` INTEGER PRIMARY KEY AUTOINCREMENT NOT NULL, `card` INTEGER NOT NULL, `row` INTEGER NOT NULL, `column` INTEGER NOT NULL, `number` INTEGER NOT NULL, `ticket_id` INTEGER NOT NULL, FOREIGN KEY(`ticket_id`) REFERENCES `table_tickets`(`id`) ON UPDATE NO ACTION ON DELETE CASCADE )",
        "fields": [
          {
            "fieldPath": "id",
            "columnName": "id",
            "affinity": "INTEGER",
            "notNull": true
          },
          {
            "fieldPath": "card",
            "columnName": "card",
            "affinity": "INTEGER",
            "notNull": true
          },
          {
            "fieldPath": "row",
            "columnName": "row",
            "affinity": "INTEGER",
            "notNull": true
          },
          {
            "fieldPath": "column",
            "columnName": "column",
            "affinity": "INTEGER",
            "notNull": true
          },
          {
            "fieldPath": "number",
            "columnName": "number",
            "affinity": "INTEGER",
            "notNull": true
          },
          {
            "fieldPath": "ticket_id",
            "columnName": "ticket_id",
            "affinity": "INTEGER",
            "notNull": true
          }
        ],
        "primaryKey": {
          "autoGenerate": true,
          "columnNames": [
            "id"
          ]
        },
        "indices": [],
        "foreignKeys": [
          {
            "table": "table_tickets",
            "onDelete": "CASCADE",
            "onUpdate": "NO ACTION",
            "columns": [
              "ticket_id"
            ],
            "referencedColumns": [
              "id"
            ]
          }
        ]
      }
    ],
    "views": [],
    "setupQueries": [
      "CREATE TABLE IF NOT EXISTS room_master_table (id INTEGER PRIMARY KEY,identity_hash TEXT)",
      "INSERT OR REPLACE INTO room_master_table (id,identity_hash) VALUES(42, 'e159e5c263765134655d74ff72689d00')"
    ]
  }
}